verilog/projeto/controle.v
module controle(instrucao, MemToReg, LeMem, EscMem, ALUOp, Jump, ALUSrc, EscReg1, EscReg2, Halt);

input [7:0] instrucao;
output reg ALUOp, Jump, LeMem, EscMem, ALUSrc, EscReg1, EscReg2, Halt;
output reg [1:0] MemToReg;

always @(instrucao) begin
    // Valores padrão
    MemToReg = 2'b00;
    LeMem = 0;
    EscMem = 0;
    ALUOp = 0;
    Jump = 0;
    ALUSrc = 0;
    EscReg1 = 0;
    EscReg2 = 0;
    Halt = 0;
    
    case (instrucao[7:5]) 
        3'b000: begin // STORE
            EscMem = 1;
        end
        
        3'b001: begin // LOAD
            LeMem = 1;
            EscReg2 = 1;
        end
        
        3'b010: begin // LOADI
            MemToReg = 2'b01;
            EscReg2 = 1;
        end
        
        3'b011: begin // JUMP
           Jump = 1;
        end

        3'b100: begin // INC ou DEC
            if (instrucao[0]) begin
                ALUOp = 0;  // INC
            end 

            else begin
                ALUOp = 1;  // DEC
            end

            MemToReg = 2'b10;
            ALUSrc = 1;
            EscReg2 = 1;
        end

        3'b101: begin // SWAP
           EscReg1 = 1;
           EscReg2 = 1;
        end

        3'b110: begin // CMP
           ALUOp = 1;
        end

        3'b111: begin // HALT
           Halt = 1;
        end

    endcase
end

endmodule

verilog/projeto/controleTB.v
module controleTB;

// Sinais de teste
reg [7:0] instrucao;
wire [1:0] MemToReg;
wire LeMem, EscMem, ALUOp, Jump, ALUSrc, EscReg1, EscReg2, Halt;

// Instância do módulo controle
controle ctrl(instrucao, MemToReg, LeMem, EscMem, ALUOp, Jump, ALUSrc, EscReg1, EscReg2, Halt);

// Geração de formas de onda
initial begin
    $dumpfile("controleTB.vcd");
    $dumpvars(0, controleTB);
    
    // STORE (000)
    instrucao = 8'b00000000;
    #10;
    $display("STORE (000):");
    $display("  MemToReg: %b, LeMem: %b, EscMem: %b", MemToReg, LeMem, EscMem);
    $display("  ALUOp: %b, Jump: %b, ALUSrc: %b", ALUOp, Jump, ALUSrc);
    $display("  EscReg1: %b, EscReg2: %b, Halt: %b", EscReg1, EscReg2, Halt);
    $display("");
    
    // LOAD (001)
    instrucao = 8'b00100000;
    #10;
    $display("LOAD (001):");
    $display("  MemToReg: %b, LeMem: %b, EscMem: %b", MemToReg, LeMem, EscMem);
    $display("  ALUOp: %b, Jump: %b, ALUSrc: %b", ALUOp, Jump, ALUSrc);
    $display("  EscReg1: %b, EscReg2: %b, Halt: %b", EscReg1, EscReg2, Halt);
    $display("");
    
    // LOADI (010)
    instrucao = 8'b01000000;
    #10;
    $display("LOADI (010):");
    $display("  MemToReg: %b, LeMem: %b, EscMem: %b", MemToReg, LeMem, EscMem);
    $display("  ALUOp: %b, Jump: %b, ALUSrc: %b", ALUOp, Jump, ALUSrc);
    $display("  EscReg1: %b, EscReg2: %b, Halt: %b", EscReg1, EscReg2, Halt);
    $display("");
    
    // JUMP (011)
    instrucao = 8'b01100000;
    #10;
    $display("JUMP (011):");
    $display("  MemToReg: %b, LeMem: %b, EscMem: %b", MemToReg, LeMem, EscMem);
    $display("  ALUOp: %b, Jump: %b, ALUSrc: %b", ALUOp, Jump, ALUSrc);
    $display("  EscReg1: %b, EscReg2: %b, Halt: %b", EscReg1, EscReg2, Halt);
    $display("");
    
    // DEC (100 com bit 0 = 0)
    instrucao = 8'b10000000;
    #10;
    $display("DEC (100, funct = 0):");
    $display("  MemToReg: %b, LeMem: %b, EscMem: %b", MemToReg, LeMem, EscMem);
    $display("  ALUOp: %b, Jump: %b, ALUSrc: %b", ALUOp, Jump, ALUSrc);
    $display("  EscReg1: %b, EscReg2: %b, Halt: %b", EscReg1, EscReg2, Halt);
    $display("");
    
    // INC (100 com bit 0 = 1)
    instrucao = 8'b10000001;
    #10;
    $display("INC (100, funct = 1):");
    $display("  MemToReg: %b, LeMem: %b, EscMem: %b", MemToReg, LeMem, EscMem);
    $display("  ALUOp: %b, Jump: %b, ALUSrc: %b", ALUOp, Jump, ALUSrc);
    $display("  EscReg1: %b, EscReg2: %b, Halt: %b", EscReg1, EscReg2, Halt);
    $display("");
    
    // SWAP (101)
    instrucao = 8'b10100000;
    #10;
    $display("SWAP (101):");
    $display("  MemToReg: %b, LeMem: %b, EscMem: %b", MemToReg, LeMem, EscMem);
    $display("  ALUOp: %b, Jump: %b, ALUSrc: %b", ALUOp, Jump, ALUSrc);
    $display("  EscReg1: %b, EscReg2: %b, Halt: %b", EscReg1, EscReg2, Halt);
    $display("");
    
    // CMP (110)
    instrucao = 8'b11000000;
    #10;
    $display("CMP (110):");
    $display("  MemToReg: %b, LeMem: %b, EscMem: %b", MemToReg, LeMem, EscMem);
    $display("  ALUOp: %b, Jump: %b, ALUSrc: %b", ALUOp, Jump, ALUSrc);
    $display("  EscReg1: %b, EscReg2: %b, Halt: %b", EscReg1, EscReg2, Halt);
    $display("");
    
    // HALT (111)
    instrucao = 8'b11100000;
    #10;
    $display("HALT (111):");
    $display("  MemToReg: %b, LeMem: %b, EscMem: %b", MemToReg, LeMem, EscMem);
    $display("  ALUOp: %b, Jump: %b, ALUSrc: %b", ALUOp, Jump, ALUSrc);
    $display("  EscReg1: %b, EscReg2: %b, Halt: %b", EscReg1, EscReg2, Halt);
    $display("");
    
    $finish;
end

endmodule

verilog/projeto/controleTB.vcd
$date
	Thu Jul 03 20:30:05 2025
$end
$version
	Icarus Verilog
$end
$timescale
	1s
$end
$scope module controleTB $end
$var wire 2 ! MemToReg [1:0] $end
$var wire 1 " LeMem $end
$var wire 1 # Jump $end
$var wire 1 $ Halt $end
$var wire 1 % EscReg2 $end
$var wire 1 & EscReg1 $end
$var wire 1 ' EscMem $end
$var wire 1 ( ALUSrc $end
$var wire 1 ) ALUOp $end
$var reg 8 * instrucao [7:0] $end
$scope module ctrl $end
$var wire 8 + instrucao [7:0] $end
$var reg 1 ) ALUOp $end
$var reg 1 ( ALUSrc $end
$var reg 1 ' EscMem $end
$var reg 1 & EscReg1 $end
$var reg 1 % EscReg2 $end
$var reg 1 $ Halt $end
$var reg 1 # Jump $end
$var reg 1 " LeMem $end
$var reg 2 , MemToReg [1:0] $end
$upscope $end
$upscope $end
$enddefinitions $end
$comment Show the parameter values. $end
$dumpall
$end
#0
$dumpvars
b0 ,
b0 +
b0 *
0)
0(
1'
0&
0%
0$
0#
0"
b0 !
$end
#10
1%
1"
0'
b100000 *
b100000 +
#20
b1 !
b1 ,
1%
0"
b1000000 *
b1000000 +
#30
1#
0%
b0 !
b0 ,
b1100000 *
b1100000 +
#40
1%
1(
b10 !
b10 ,
1)
0#
b10000000 *
b10000000 +
#50
1%
1(
0)
b10 !
b10 ,
b10000001 *
b10000001 +
#60
1&
1%
0(
b0 !
b0 ,
b10100000 *
b10100000 +
#70
1)
0%
0&
b11000000 *
b11000000 +
#80
1$
0)
b11100000 *
b11100000 +
